{
  "0": "ffffff",
  "1": "ffffff",
  "2": "ffffff",
  "3": "ffffff",
  "4": "ffffff",
  "5": "ffffff",
  "6": "ffffff",
  "7": "ffffff",
  "8": "ffffff",
  "9": "ffffff",
  "ESC": "ffffff",
  "F1": "ffffff",
  "F2": "ffffff",
  "F3": "ffffff",
  "F4": "ffffff",
  "F5": "ffffff",
  "F6": "ffffff",
  "F7": "ffffff",
  "F8": "ffffff",
  "F9": "ffffff",
  "F10": "ffffff",
  "F11": "ffffff",
  "F12": "ffffff",
  "`": "ffffff",
  "-": "ffffff",
  "=": "ffffff",
  "BACKSPACE": "ffffff",
  "TAB": "ffffff",
  "Q": "ffffff",
  "W": "ff0000",
  "E": "ffffff",
  "R": "ffffff",
  "T": "ffffff",
  "Y": "ffffff",
  "U": "ffffff",
  "I": "ffffff",
  "O": "ffffff",
  "P": "ffffff",
  "[": "ffffff",
  "]": "ffffff",
  "BACKSLASH": "ffffff",
  "CAPS": "ffffff",
  "A": "ff0000",
  "S": "ff0000",
  "D": "ff0000",
  "F": "ffffff",
  "G": "ffffff",
  "H": "ffffff",
  "J": "ffffff",
  "K": "ffffff",
  "L": "ffffff",
  ";": "ffffff",
  "'": "ffffff",
  "ENTER": "ffffff",
  "SHIFT_L": "ffffff",
  "Z": "ffffff",
  "X": "ffffff",
  "C": "ffffff",
  "V": "ffffff",
  "B": "ffffff",
  "N": "ffffff",
  "M": "ffffff",
  ",": "ffffff",
  ".": "ffffff",
  "/": "ffffff",
  "SHIFT_R": "ffffff",
  "CTRL_L": "ffffff",
  "WIN": "ffffff",
  "ALT_L": "ffffff",
  "SPACEBAR": "ffffff",
  "ALT_R": "ffffff",
  "FN": "ffffff",
  "MENU": "ffffff",
  "CTRL_R": "ffffff",
  "INS": "ffffff",
  "HM": "ffffff",
  "PU": "ffffff",
  "DEL": "ffffff",
  "END": "ffffff",
  "PD": "ffffff",
  "UP": "ffffff",
  "LEFT": "ffffff",
  "DOWN": "ffffff",
  "RIGHT": "ffffff",
  "PB": "ffffff",
  "SL": "ffffff",
  "PS": "ffffff",
  "NUMLOCK": "ffffff",
  "KPSLASH": "ffffff",
  "KPASTERISK": "ffffff",
  "KPMINUS": "ffffff",
  "KPPLUS": "ffffff",
  "KP1": "ffffff",
  "KP2": "ffffff",
  "KP3": "ffffff",
  "KP4": "ffffff",
  "KP5": "ffffff",
  "KP6": "ffffff",
  "KP7": "ffffff",
  "KP8": "ffffff",
  "KP9": "ffffff",
  "KP0": "ffffff",
  "KPDOT": "ffffff",
  "KPENTER": "ffffff"
}